pelican/themes/orbelican/__init__.py
pelican/themes/orbelican/data/config.json
pelican/themes/orbelican/data/profile.json
pelican/themes/orbelican/data/resume.json
pelican/themes/orbelican/static/favicon.ico
pelican/themes/orbelican/static/css/orbit-1.css
pelican/themes/orbelican/static/css/orbit-2.css
pelican/themes/orbelican/static/css/orbit-3.css
pelican/themes/orbelican/static/css/orbit-4.css
pelican/themes/orbelican/static/css/orbit-5.css
pelican/themes/orbelican/static/css/orbit-6.css
pelican/themes/orbelican/static/css/orbit-7.css
pelican/themes/orbelican/static/images/profile.png
pelican/themes/orbelican/static/js/main.js
pelican/themes/orbelican/static/plugins/bootstrap/bootstrap.min.css
pelican/themes/orbelican/static/plugins/bootstrap/bootstrap.min.css.map
pelican/themes/orbelican/static/plugins/bootstrap/bootstrap.min.js
pelican/themes/orbelican/static/plugins/bootstrap/bootstrap.min.js.map
pelican/themes/orbelican/static/plugins/fontawesome/fontawesome.min.css
pelican/themes/orbelican/static/plugins/fontawesome/fontawesome.min.js
pelican/themes/orbelican/static/plugins/fontawesome/webfonts/fa-brands-400.eot
pelican/themes/orbelican/static/plugins/fontawesome/webfonts/fa-brands-400.svg
pelican/themes/orbelican/static/plugins/fontawesome/webfonts/fa-brands-400.ttf
pelican/themes/orbelican/static/plugins/fontawesome/webfonts/fa-brands-400.woff
pelican/themes/orbelican/static/plugins/fontawesome/webfonts/fa-brands-400.woff2
pelican/themes/orbelican/static/plugins/fontawesome/webfonts/fa-regular-400.eot
pelican/themes/orbelican/static/plugins/fontawesome/webfonts/fa-regular-400.svg
pelican/themes/orbelican/static/plugins/fontawesome/webfonts/fa-regular-400.ttf
pelican/themes/orbelican/static/plugins/fontawesome/webfonts/fa-regular-400.woff
pelican/themes/orbelican/static/plugins/fontawesome/webfonts/fa-regular-400.woff2
pelican/themes/orbelican/static/plugins/fontawesome/webfonts/fa-solid-900.eot
orbelican-1.0.0.dist-info/LICENSE
orbelican-1.0.0.dist-info/METADATA
orbelican-1.0.0.dist-info/WHEEL
orbelican-1.0.0.dist-info/top_level.txt
orbelican-1.0.0.dist-info/zip-safe
orbelican-1.0.0.dist-info/RECORD
