Metadata-Version: 2.1
Name: orbelican
Version: 1.0.0
Summary: A simple port of orbit-theme for Pelican to build an online resume
Home-page: https://github.com/LucasVanHaaren/orbelican
Author: vhash
Author-email: vanhaaren.lucas+dev@gmail.com
License: MIT
Keywords: pelican,pelican-theme,orbit,orbit-theme,resume,portfolio
Platform: UNKNOWN
Classifier: Framework :: Pelican :: Themes
Classifier: Intended Audience :: Developers
Classifier: Intended Audience :: End Users/Desktop
Classifier: License :: OSI Approved :: MIT License
Requires-Dist: pelican
Requires-Dist: pelican-data-files (>=1.1.0)
Provides-Extra: dev
Requires-Dist: libsass (>=0.20.0) ; extra == 'dev'
Requires-Dist: invoke ; extra == 'dev'
Requires-Dist: twine ; extra == 'dev'
